gotennet/__init__.py
gotennet/testing_pipeline.py
gotennet/training_pipeline.py
gotennet/configs/__init__.py
gotennet/configs/test.yaml
gotennet/configs/train.yaml
gotennet/configs/callbacks/default.yaml
gotennet/configs/callbacks/none.yaml
gotennet/configs/datamodule/qm9.yaml
gotennet/configs/experiment/qm9.yaml
gotennet/configs/experiment/qm9_u0.yaml
gotennet/configs/hydra/default.yaml
gotennet/configs/hydra/job_logging/logger.yaml
gotennet/configs/logger/comet.yaml
gotennet/configs/logger/csv.yaml
gotennet/configs/logger/default.yaml
gotennet/configs/logger/many_loggers.yaml
gotennet/configs/logger/mlflow.yaml
gotennet/configs/logger/neptune.yaml
gotennet/configs/logger/tensorboard.yaml
gotennet/configs/logger/wandb.yaml
gotennet/configs/model/gotennet.yaml
gotennet/configs/paths/default.yaml
gotennet/configs/trainer/default.yaml
gotennet/datamodules/__init__.py
gotennet/datamodules/datamodule.py
gotennet/datamodules/components/__init__.py
gotennet/datamodules/components/qm9.py
gotennet/datamodules/components/utils.py
gotennet/models/__init__.py
gotennet/models/goten_model.py
gotennet/models/components/__init__.py
gotennet/models/components/layers.py
gotennet/models/components/outputs.py
gotennet/models/representation/gotennet.py
gotennet/models/tasks/QM9Task.py
gotennet/models/tasks/Task.py
gotennet/models/tasks/__init__.py
gotennet/scripts/__init__.py
gotennet/scripts/test.py
gotennet/scripts/train.py
gotennet/utils/__init__.py
gotennet/utils/file.py
gotennet/utils/logging_utils.py
gotennet/utils/utils.py
gotennet/vendor/__init__.py
gotennet-1.1.2.dist-info/METADATA
gotennet-1.1.2.dist-info/WHEEL
gotennet-1.1.2.dist-info/entry_points.txt
gotennet-1.1.2.dist-info/licenses/LICENSE
gotennet-1.1.2.dist-info/RECORD
