Metadata-Version: 2.4
Name: gotennet
Version: 1.1.2
Summary: GotenNet: Rethinking Efficient 3D Equivariant Graph Neural Networks
Project-URL: Homepage, https://github.com/sarpaykent/gotennet
Project-URL: Bug Tracker, https://github.com/sarpaykent/gotennet/issues
Author: GotenNet Authors
License: MIT License
License-File: LICENSE
Classifier: Development Status :: 4 - Beta
Classifier: Intended Audience :: Science/Research
Classifier: License :: OSI Approved :: MIT License
Classifier: Programming Language :: Python :: 3
Classifier: Programming Language :: Python :: 3.10
Classifier: Topic :: Scientific/Engineering
Classifier: Topic :: Scientific/Engineering :: Artificial Intelligence
Classifier: Topic :: Scientific/Engineering :: Chemistry
Requires-Python: >=3.10
Requires-Dist: ase
Requires-Dist: e3nn
Requires-Dist: numpy
Requires-Dist: torch-cluster
Requires-Dist: torch-geometric
Requires-Dist: torch-scatter
Requires-Dist: torch-sparse
Requires-Dist: torch>=2.5.0
Provides-Extra: dev
Requires-Dist: black; extra == 'dev'
Requires-Dist: isort; extra == 'dev'
Requires-Dist: mypy; extra == 'dev'
Requires-Dist: pytest; extra == 'dev'
Requires-Dist: pytest-cov; extra == 'dev'
Requires-Dist: ruff; extra == 'dev'
Provides-Extra: docs
Requires-Dist: sphinx; extra == 'docs'
Requires-Dist: sphinx-rtd-theme; extra == 'docs'
Provides-Extra: full
Requires-Dist: hydra-colorlog; extra == 'full'
Requires-Dist: hydra-core; extra == 'full'
Requires-Dist: hydra-optuna-sweeper; extra == 'full'
Requires-Dist: lightning==2.2.5; extra == 'full'
Requires-Dist: omegaconf; extra == 'full'
Requires-Dist: pandas; extra == 'full'
Requires-Dist: pyg-lib; extra == 'full'
Requires-Dist: pyrootutils; extra == 'full'
Requires-Dist: python-dotenv; extra == 'full'
Requires-Dist: pytorch-lightning==2.2.5; extra == 'full'
Requires-Dist: rdkit; extra == 'full'
Requires-Dist: rich; extra == 'full'
Requires-Dist: scikit-learn; extra == 'full'
Requires-Dist: torch-spline-conv; extra == 'full'
Requires-Dist: torchaudio; extra == 'full'
Requires-Dist: torchvision; extra == 'full'
Requires-Dist: wandb; extra == 'full'
